fleettracker/__init__.py
fleettracker/admin.py
fleettracker/app_settings.py
fleettracker/apps.py
fleettracker/auth_hooks.py
fleettracker/forms.py
fleettracker/models.py
fleettracker/services.py
fleettracker/tasks.py
fleettracker/urls.py
fleettracker/views.py
fleettracker/locale/.gitkeep
fleettracker/migrations/0001_initial.py
fleettracker/migrations/0002_fleetsnapshot_alter_general_options_and_more.py
fleettracker/migrations/0003_fleettrackerusersettings.py
fleettracker/migrations/0004_alter_fleetmembersnapshot_solar_system_id.py
fleettracker/migrations/__init__.py
fleettracker/static/fleettracker/.gitkeep
fleettracker/templates/fleettracker/base.html
fleettracker/templates/fleettracker/dashboard.html
fleettracker/templates/fleettracker/fleet_detail.html
fleettracker/templatetags/__init__.py
fleettracker/templatetags/fleettracker_tags.py
fleettracker/tests/__init__.py
fleettracker/tests/test_example.py
aa_fleettracker-1.0.0.dist-info/METADATA
aa_fleettracker-1.0.0.dist-info/WHEEL
aa_fleettracker-1.0.0.dist-info/licenses/LICENSE
aa_fleettracker-1.0.0.dist-info/RECORD
